aaqnumtowords/__init__.py
aaqnumtowords/aaqnumtowords.py
aaqnumtowords-0.0.4.dist-info/LICENSE
aaqnumtowords-0.0.4.dist-info/METADATA
aaqnumtowords-0.0.4.dist-info/WHEEL
aaqnumtowords-0.0.4.dist-info/top_level.txt
aaqnumtowords-0.0.4.dist-info/RECORD
