Metadata-Version: 2.2
Name: aaqnumtowords
Version: 0.0.4
Summary: A Python package for converting numbers to text
Author-email: Ali Ayati Qaffari <ayatiali910@gmail.com>
License: MIT License
Project-URL: Profile, https://github.com/MrAAQPy
Project-URL: github, https://github.com/MrAAQPy/aaqnumtowords
Project-URL: issue, https://github.com/MrAAQPy/aaqnumtowords/issues
Project-URL: bale, https://ble.ir/aaq1386
Requires-Python: >=3.1
License-File: LICENSE
